itaxotools/taxi2/__init__.py
itaxotools/taxi2/align.py
itaxotools/taxi2/distances.py
itaxotools/taxi2/encoding.py
itaxotools/taxi2/file_types.py
itaxotools/taxi2/files.py
itaxotools/taxi2/handlers.py
itaxotools/taxi2/pairs.py
itaxotools/taxi2/partitions.py
itaxotools/taxi2/plot.py
itaxotools/taxi2/sequences.py
itaxotools/taxi2/statistics.py
itaxotools/taxi2/trees.py
itaxotools/taxi2/types.py
itaxotools/taxi2/tasks/__init__.py
itaxotools/taxi2/tasks/decontaminate.py
itaxotools/taxi2/tasks/decontaminate2.py
itaxotools/taxi2/tasks/dereplicate.py
itaxotools/taxi2/tasks/versus_all.py
itaxotools/taxi2/tasks/versus_reference.py
itaxotools_taxi2-2.2.2.dist-info/licenses/LICENSE
itaxotools_taxi2-2.2.2.dist-info/METADATA
itaxotools_taxi2-2.2.2.dist-info/WHEEL
itaxotools_taxi2-2.2.2.dist-info/entry_points.txt
itaxotools_taxi2-2.2.2.dist-info/top_level.txt
itaxotools_taxi2-2.2.2.dist-info/RECORD
