Metadata-Version: 2.4
Name: itaxotools-taxi2
Version: 2.2.2
Summary: Calculation and analysis of pairwise sequence distances
Author-email: Stefanos Patmanidis <stefanpatman91@gmail.com>, Vladimir Kharchev <necrosovereign@gmail.com>
Project-URL: Homepage, https://itaxotools.org/
Project-URL: Source, https://github.com/iTaxoTools/TaxI2
Classifier: License :: OSI Approved :: GNU General Public License v3 or later (GPLv3+)
Classifier: Development Status :: 5 - Production/Stable
Classifier: Programming Language :: Python
Classifier: Programming Language :: Python :: 3.10
Classifier: Programming Language :: Python :: 3.11
Classifier: Programming Language :: Python :: 3.12
Classifier: Programming Language :: Python :: 3.13
Classifier: Programming Language :: Python :: Implementation :: CPython
Requires-Python: <4,>=3.10.2
License-File: LICENSE
Requires-Dist: itaxotools-common
Requires-Dist: itaxotools-spart-parser
Requires-Dist: itaxotools-calculate-distances
Requires-Dist: BioPython>=1.84
Requires-Dist: alfpy
Requires-Dist: numpy
Requires-Dist: openpyxl
Requires-Dist: pandas
Requires-Dist: seaborn
Provides-Extra: dev
Requires-Dist: setuptools-scm; extra == "dev"
Requires-Dist: pre-commit; extra == "dev"
Requires-Dist: ruff; extra == "dev"
Requires-Dist: pytest; extra == "dev"
Requires-Dist: pytest-cov; extra == "dev"
Requires-Dist: coverage; extra == "dev"
Dynamic: license-file
